SharesightAPI/SharesightAPI.py
SharesightAPI/__init__.py
SharesightAPI-1.1.18.dist-info/METADATA
SharesightAPI-1.1.18.dist-info/WHEEL
SharesightAPI-1.1.18.dist-info/top_level.txt
SharesightAPI-1.1.18.dist-info/RECORD
