Metadata-Version: 2.1
Name: SharesightAPI
Version: 1.1.18
Summary: A Python library to access your sharesight portfolio information
Home-page: https://github.com/Poshy163/Sharesight-API
Author: Joshua Leaper
Author-email: poshernater163@gmail.com
Classifier: Programming Language :: Python :: 3
Classifier: License :: OSI Approved :: MIT License
Classifier: Operating System :: OS Independent
